provider_fireworks.py
opsmate_provider_fireworks-0.1.1a0.dist-info/METADATA
opsmate_provider_fireworks-0.1.1a0.dist-info/WHEEL
opsmate_provider_fireworks-0.1.1a0.dist-info/entry_points.txt
opsmate_provider_fireworks-0.1.1a0.dist-info/licenses/LICENSE
opsmate_provider_fireworks-0.1.1a0.dist-info/RECORD
