Metadata-Version: 2.4
Name: opsmate-provider-fireworks
Version: 0.1.1a0
Summary: Fireworks AI provider for opsmate
Author-email: Jingkai He <jingkai@hey.com>
License: MIT License
License-File: LICENSE
Requires-Python: <4.0,>=3.10
Requires-Dist: fireworks-ai>=0.15.12
Requires-Dist: opsmate
